<annotation>
	<folder>Care tags</folder>
	<filename>20220218_172609.jpg</filename>
	<path>D:\Projects\durhack2022\MeanCleanWashingMachine\images\Care tags\20220218_172609.jpg</path>
	<source>
		<database>Unknown</database>
	</source>
	<size>
		<width>998</width>
		<height>1171</height>
		<depth>3</depth>
	</size>
	<segmented>0</segmented>
	<object>
		<name>wash at or below 40</name>
		<pose>Unspecified</pose>
		<truncated>0</truncated>
		<difficult>0</difficult>
		<bndbox>
			<xmin>230</xmin>
			<ymin>571</ymin>
			<xmax>359</xmax>
			<ymax>672</ymax>
		</bndbox>
	</object>
	<object>
		<name>do not bleach</name>
		<pose>Unspecified</pose>
		<truncated>0</truncated>
		<difficult>0</difficult>
		<bndbox>
			<xmin>358</xmin>
			<ymin>573</ymin>
			<xmax>458</xmax>
			<ymax>667</ymax>
		</bndbox>
	</object>
	<object>
		<name>do not tumble dry</name>
		<pose>Unspecified</pose>
		<truncated>0</truncated>
		<difficult>0</difficult>
		<bndbox>
			<xmin>454</xmin>
			<ymin>572</ymin>
			<xmax>562</xmax>
			<ymax>657</ymax>
		</bndbox>
	</object>
	<object>
		<name>iron medium temp</name>
		<pose>Unspecified</pose>
		<truncated>0</truncated>
		<difficult>0</difficult>
		<bndbox>
			<xmin>562</xmin>
			<ymin>567</ymin>
			<xmax>667</xmax>
			<ymax>660</ymax>
		</bndbox>
	</object>
	<object>
		<name>dry clean</name>
		<pose>Unspecified</pose>
		<truncated>0</truncated>
		<difficult>0</difficult>
		<bndbox>
			<xmin>668</xmin>
			<ymin>555</ymin>
			<xmax>755</xmax>
			<ymax>655</ymax>
		</bndbox>
	</object>
</annotation>
